soundbyte/__init__.py
soundbyte/cli/__init__.py
soundbyte/cli/main.py
soundbyte/components/__init__.py
soundbyte/components/audit_ops/__init__.py
soundbyte/components/audit_ops/classification_regression.py
soundbyte/components/audit_ops/distillation.py
soundbyte/components/audit_ops/mtsq_quantizer.py
soundbyte/components/control_ops/__init__.py
soundbyte/components/control_ops/optimizers.py
soundbyte/components/data_ops/__init__.py
soundbyte/components/data_ops/cifar10_mnist.py
soundbyte/components/model_ops/__init__.py
soundbyte/components/model_ops/architectures.py
soundbyte/components/penalty_ops/__init__.py
soundbyte/components/penalty_ops/losses.py
soundbyte/components/schedule_ops/__init__.py
soundbyte/components/schedule_ops/schedulers.py
soundbyte/components/train_ops/__init__.py
soundbyte/components/train_ops/classification.py
soundbyte/components/train_ops/distillation.py
soundbyte/config/__init__.py
soundbyte/config/experiment.py
soundbyte/core/__init__.py
soundbyte/core/factory.py
soundbyte/core/interfaces.py
soundbyte/execution/__init__.py
soundbyte/execution/runner.py
soundbyte/plugins/__init__.py
soundbyte/plugins/registry.py
soundbyte/utils/__init__.py
soundbyte/utils/mtsq_utils.py
soundbyte/utils/onnx_utils.py
soundbyte/utils/profiler.py
soundbyte-0.1.3.dist-info/licenses/LICENSE
soundbyte-0.1.3.dist-info/METADATA
soundbyte-0.1.3.dist-info/WHEEL
soundbyte-0.1.3.dist-info/entry_points.txt
soundbyte-0.1.3.dist-info/top_level.txt
soundbyte-0.1.3.dist-info/RECORD
