Metadata-Version: 2.4
Name: soundbyte
Version: 0.1.3
Summary: Learn, Train, Deploy: An Academic-friendly DL Toolkit for Accelerated Learning and Prototyping
Author-email: Vishal Kumar <vishalku@iiitd.ac.in>
Requires-Python: >=3.12
License-File: LICENSE
Requires-Dist: torch>=2.0.0
Requires-Dist: torchvision>=0.15.0
Requires-Dist: torchaudio>=2.0.0
Requires-Dist: typer>=0.9.0
Requires-Dist: matplotlib>=3.7.0
Requires-Dist: rich>=10.0.0
Requires-Dist: pydantic>=2.0.0
Requires-Dist: numpy>=1.24.0
Requires-Dist: Pillow>=9.0.0
Requires-Dist: tqdm>=4.64.0
Requires-Dist: scikit-learn>=1.0.0
Requires-Dist: PyYAML>=5.4.0
Dynamic: license-file
